stellar/__init__.py
stellar/__main__.py
stellar/config.py
stellar/server.py
stellar/functions/builtin.py
stellar/types/builtin.py
stellar_lang-0.1.2.dist-info/METADATA
stellar_lang-0.1.2.dist-info/WHEEL
stellar_lang-0.1.2.dist-info/entry_points.txt
stellar_lang-0.1.2.dist-info/top_level.txt
stellar_lang-0.1.2.dist-info/RECORD
