Metadata-Version: 2.4
Name: stellar-lang
Version: 0.1.2
Summary: STELLAR: A Simple Tool for Exploring and Analyzing Tabulated Data in Python
Author-email: Stefan Nožinić <stefan@lugons.org>
Requires-Python: >=3.8
Requires-Dist: pandas
Requires-Dist: numpy
Requires-Dist: tabulate
Requires-Dist: pygls
Requires-Dist: tatsu
Requires-Dist: orgasm-package
